[
  {
    "color": "green",
    "collectable": true,
    "key": "normal_mobs",
    "locations": [
      {
        "key": "shaman_chankaki_1",
        "x": -12.14388021,
        "y": 39.72591146
      },
      {
        "key": "shaman_chankaki_1",
        "x": -10.88606771,
        "y": 38.73763021
      },
      {
        "key": "shaman_chankaki_1",
        "x": -9.658203125,
        "y": 39.74088542
      },
      {
        "key": "shaman_chankaki_1",
        "x": -9.852864583,
        "y": 38.33333333
      },
      {
        "key": "lonely_mepisto_7",
        "x": -29.54361979,
        "y": 40.86393229
      },
      {
        "key": "lonely_mepisto_8",
        "x": -27.44726563,
        "y": 38.72265625
      },
      {
        "key": "lonely_mepisto_9",
        "x": -30.56184896,
        "y": 38.73763021
      },
      {
        "key": "wind_spirit_shalph_8",
        "x": -33.01,
        "y": 24.96009115
      },
      {
        "key": "wind_spirit_shalph_9",
        "x": -32.76152344,
        "y": 26.07115885
      },
      {
        "key": "wind_spirit_shalph_10",
        "x": -36.55592448,
        "y": 27.61347656
      },
      {
        "key": "wind_spirit_shalph_11",
        "x": -34.35175781,
        "y": 28.7859375
      },
      {
        "key": "abandoned_cargo_9",
        "x": -35,
        "y": 12.25
      },
      {
        "key": "aishi_10",
        "x": -32.1018416152344,
        "y": 29.573172889974
      },
      {
        "key": "aishi_11",
        "x": -32.4466045625,
        "y": 26.2942799674479
      },
      {
        "key": "aishi_12",
        "x": -32.9882918925781,
        "y": 29.7435930520833
      },
      {
        "key": "aishi_13",
        "x": -33.9493962916667,
        "y": 24.3713272480469
      },
      {
        "key": "aishi_14",
        "x": -33.142575578125,
        "y": 24.86976703125
      },
      {
        "key": "lamega_17",
        "x": -37.6,
        "y": 13.25
      },
      {
        "key": "suspicious_box_19",
        "x": -26.0382165052083,
        "y": 38.00390625
      }
    ]
  },
  {
    "color": "yellow",
    "collectable": true,
    "key": "elite_mobs",
    "locations": [
      {
        "key": "paksigue_1",
        "x": -23.07486979,
        "y": 21.59244792
      },
      {
        "key": "hakka_the_bigmouth_2",
        "x": -28.8415034635417,
        "y": 15.8507592721354
      },
      {
        "key": "scrapper_tunkara_3",
        "x": -27.7858394010417,
        "y": 11.3389988769531
      },
      {
        "key": "blindeye_4",
        "x": -30.268655859375,
        "y": 15.3383727890625
      },
      {
        "key": "scrapper_kuntura_5",
        "x": -32.0527229290365,
        "y": 14.0732305065104
      },
      {
        "key": "kumbacha_the_shaman_6",
        "x": -31.0121059427083,
        "y": 16.6929329173177
      },
      {
        "key": "scout_takata_15",
        "x": -33.164952436849,
        "y": 19.4859764602865
      },
      {
        "key": "smackstopper_tambaku_16",
        "x": -36.2188612610677,
        "y": 17.6238993053385
      }
    ]
  },
  {
    "color": "red",
    "collectable": true,
    "key": "heroic_mobs",
    "locations": [
      {
        "key": "chieftain_kraka_18",
        "x": -39.1872839967448,
        "y": 16.6416299348958
      }
    ]
  }
]